JiyuEosNodeJsDeDappGongchengxiangmuShizhanQuZhongxinhuaJiaoyisuo/README.md
JiyuEosNodeJsDeDappGongchengxiangmuShizhanQuZhongxinhuaJiaoyisuo/__init__.py
JiyuEosNodeJsDeDappGongchengxiangmuShizhanQuZhongxinhuaJiaoyisuo/__main__.py
JiyuEosNodeJsDeDappGongchengxiangmuShizhanQuZhongxinhuaJiaoyisuo/file.epub
JiyuEosNodeJsDeDappGongchengxiangmuShizhanQuZhongxinhuaJiaoyisuo/index.html
JiyuEosNodeJsDeDappGongchengxiangmuShizhanQuZhongxinhuaJiaoyisuo/css/__init__.py
JiyuEosNodeJsDeDappGongchengxiangmuShizhanQuZhongxinhuaJiaoyisuo/css/annotations.css
JiyuEosNodeJsDeDappGongchengxiangmuShizhanQuZhongxinhuaJiaoyisuo/css/main.css
JiyuEosNodeJsDeDappGongchengxiangmuShizhanQuZhongxinhuaJiaoyisuo/css/normalize.css
JiyuEosNodeJsDeDappGongchengxiangmuShizhanQuZhongxinhuaJiaoyisuo/css/popup.css
JiyuEosNodeJsDeDappGongchengxiangmuShizhanQuZhongxinhuaJiaoyisuo/font/__init__.py
JiyuEosNodeJsDeDappGongchengxiangmuShizhanQuZhongxinhuaJiaoyisuo/font/fontello.eot
JiyuEosNodeJsDeDappGongchengxiangmuShizhanQuZhongxinhuaJiaoyisuo/font/fontello.svg
JiyuEosNodeJsDeDappGongchengxiangmuShizhanQuZhongxinhuaJiaoyisuo/font/fontello.ttf
JiyuEosNodeJsDeDappGongchengxiangmuShizhanQuZhongxinhuaJiaoyisuo/font/fontello.woff
JiyuEosNodeJsDeDappGongchengxiangmuShizhanQuZhongxinhuaJiaoyisuo/img/__init__.py
JiyuEosNodeJsDeDappGongchengxiangmuShizhanQuZhongxinhuaJiaoyisuo/img/annotator-glyph-sprite.png
JiyuEosNodeJsDeDappGongchengxiangmuShizhanQuZhongxinhuaJiaoyisuo/img/annotator-icon-sprite.png
JiyuEosNodeJsDeDappGongchengxiangmuShizhanQuZhongxinhuaJiaoyisuo/img/apple-touch-icon.png
JiyuEosNodeJsDeDappGongchengxiangmuShizhanQuZhongxinhuaJiaoyisuo/img/cancelfullscreen.png
JiyuEosNodeJsDeDappGongchengxiangmuShizhanQuZhongxinhuaJiaoyisuo/img/close.png
JiyuEosNodeJsDeDappGongchengxiangmuShizhanQuZhongxinhuaJiaoyisuo/img/fullscreen.png
JiyuEosNodeJsDeDappGongchengxiangmuShizhanQuZhongxinhuaJiaoyisuo/img/loader.gif
JiyuEosNodeJsDeDappGongchengxiangmuShizhanQuZhongxinhuaJiaoyisuo/img/menu-icon.png
jiyu_eos_node_js_de_dapp_gongchengxiangmu_shizhan_qu_zhongxinhua_jiaoyisuo-2024.3.4.0.dist-info/METADATA
jiyu_eos_node_js_de_dapp_gongchengxiangmu_shizhan_qu_zhongxinhua_jiaoyisuo-2024.3.4.0.dist-info/WHEEL
jiyu_eos_node_js_de_dapp_gongchengxiangmu_shizhan_qu_zhongxinhua_jiaoyisuo-2024.3.4.0.dist-info/entry_points.txt
jiyu_eos_node_js_de_dapp_gongchengxiangmu_shizhan_qu_zhongxinhua_jiaoyisuo-2024.3.4.0.dist-info/top_level.txt
jiyu_eos_node_js_de_dapp_gongchengxiangmu_shizhan_qu_zhongxinhua_jiaoyisuo-2024.3.4.0.dist-info/RECORD
