Metadata-Version: 2.1
Name: jiyu-eos-node-js-de-dapp-gongchengxiangmu-shizhan-qu-zhongxinhua-jiaoyisuo
Version: 2024.3.4.0
Summary: 基于EOS-Node.js的DApp工程项目实战---去中心化交易所
Home-page: https://github.com/apachecn/jiyu-eos-node-js-de-dapp-gongchengxiangmu-shizhan-qu-zhongxinhua-jiaoyisuo
Author: ApacheCN
Author-email: apachecn@163.com
Classifier: Development Status :: 4 - Beta
Classifier: Environment :: Console
Classifier: Intended Audience :: Developers
Classifier: Intended Audience :: End Users/Desktop
Classifier: License :: Other/Proprietary License
Classifier: Natural Language :: Chinese (Simplified)
Classifier: Natural Language :: English
Classifier: Operating System :: OS Independent
Classifier: Programming Language :: Python :: 3
Classifier: Programming Language :: Python :: 3 :: Only
Classifier: Programming Language :: Python :: 3.6
Classifier: Programming Language :: Python :: 3.7
Classifier: Topic :: Text Processing :: Markup :: Markdown
Classifier: Topic :: Text Processing :: Markup :: HTML
Classifier: Topic :: Internet :: WWW/HTTP
Classifier: Topic :: Software Development :: Documentation
Classifier: Topic :: Documentation
Requires-Python: >=3.6
